<?xml version="1.0" encoding="utf-8"?>
<Kiri xmlns="http://www.riik.ee/schemas/kiri/">
  <AdressaatAadress>
    <AdressaatPostiaadress>
      <Maakond>Pärnu maakond</Maakond>
      <Omavalitsusyksus>Paikuse vald</Omavalitsusyksus>
      <Haldusyksus>Tammuru küla</Haldusyksus>
      <Vaikekoht>Sepa väikekoht 9</Vaikekoht>
      <Postiindeks>86605</Postiindeks>
    </AdressaatPostiaadress>
  </AdressaatAadress>
  <Adressaat>
    <AdressaatIsik>Dr Tiiu Tamm</AdressaatIsik>
    <AdressaatMarge>Sama: Vastavalt nimekirjale</AdressaatMarge>
  </Adressaat>
  <Allkirjastaja>
    <AllkiriMarge>(allkirjastatud digitaalselt)</AllkiriMarge>
    <AllkirjastajaNimi>Kati Kobar</AllkirjastajaNimi>
    <AllkirjastajaAmetinimetus>kantsler</AllkirjastajaAmetinimetus>
  </Allkirjastaja>
  <Autor>
    <AutorOrganisatsioon>MINISTEERIUM</AutorOrganisatsioon>
  </Autor>
  <AutorAadress>
    <AutorOrganisatsioonRegistrikood>Registrikood 80203639</AutorOrganisatsioonRegistrikood>
    <AutorEpost>E-post info@ministeerium.ee</AutorEpost>
    <AutorPostiaadress>
      <Omavalitsusyksus>TALLINN</Omavalitsusyksus>
      <Liikluspind>Pärnu mnt</Liikluspind>
      <Aadressinumber>158</Aadressinumber>
      <Postiindeks>15007</Postiindeks>
    </AutorPostiaadress>
  </AutorAadress>
  <AutorKontaktandmed>
    <Veebileht>www.ministeerium.ee</Veebileht>
    <Telefon>Telefon 750 0502</Telefon>
    <Faks>Faks 750 0500</Faks>
    <AutorLogo>https://www.ministeerium.ee/logo.jpg</AutorLogo>
  </AutorKontaktandmed>
  <Dokumendiliik>Kiri</Dokumendiliik>
  <Sisu>
    <Poordumine>Lugupeetud härra Kallas</Poordumine>
    <SisuLoik>Seoses peatselt avaneva EL Struktuurifondi meetme järgi on võimalus Teil kui loopealse rannaniidu omanikul taotleda toetust. Täpsema info saamiseks palun pöörduge oma piirkonna järgsesse ametisse. Kontaktid leiate www.amet.ee.</SisuLoik>
    <SisuViide>www.amet.ee</SisuViide>
    <Loputervitus>Lugupidamisega</Loputervitus>
  </Sisu>
  <Juurdepaas>
    <JuurdepaasTingimusMarge>Avalik</JuurdepaasTingimusMarge>
  </Juurdepaas>
  <Koostaja>
    <KoostajaNimi>Mati Mustikas</KoostajaNimi>
    <Telefon>656 2222</Telefon>
    <Epost>Mati.Mustikas@ministeerium.ee</Epost>
  </Koostaja>
  <DokumentKuupaev>Meie 20.01.2013</DokumentKuupaev>
  <Lisad>
    <LisaNimi>Lisa: 1. Taotlus,</LisaNimi>
    <FailNimi>taotlus</FailNimi>
    <FailVorming>.pdf</FailVorming>
  </Lisad>
  <Lisad>
    <LisaNimi>2. Taotlemise tingimused,</LisaNimi>
    <FailNimi>tingimused</FailNimi>
    <FailVorming>.pdf</FailVorming>
  </Lisad>
  <DokumentPealkiri>Teade</DokumentPealkiri>
  <DokumentViit>nr 1.1-2/4512</DokumentViit>
</Kiri>